odoo/addons/l10n_it_pec/README.rst
odoo/addons/l10n_it_pec/__init__.py
odoo/addons/l10n_it_pec/__manifest__.py
odoo/addons/l10n_it_pec/i18n/am.po
odoo/addons/l10n_it_pec/i18n/ar.po
odoo/addons/l10n_it_pec/i18n/bg.po
odoo/addons/l10n_it_pec/i18n/bs.po
odoo/addons/l10n_it_pec/i18n/ca.po
odoo/addons/l10n_it_pec/i18n/cs.po
odoo/addons/l10n_it_pec/i18n/da.po
odoo/addons/l10n_it_pec/i18n/de.po
odoo/addons/l10n_it_pec/i18n/el_GR.po
odoo/addons/l10n_it_pec/i18n/en_GB.po
odoo/addons/l10n_it_pec/i18n/es.po
odoo/addons/l10n_it_pec/i18n/es_AR.po
odoo/addons/l10n_it_pec/i18n/es_CR.po
odoo/addons/l10n_it_pec/i18n/es_EC.po
odoo/addons/l10n_it_pec/i18n/es_MX.po
odoo/addons/l10n_it_pec/i18n/es_VE.po
odoo/addons/l10n_it_pec/i18n/et.po
odoo/addons/l10n_it_pec/i18n/fi.po
odoo/addons/l10n_it_pec/i18n/fr.po
odoo/addons/l10n_it_pec/i18n/fr_CA.po
odoo/addons/l10n_it_pec/i18n/fr_CH.po
odoo/addons/l10n_it_pec/i18n/gl.po
odoo/addons/l10n_it_pec/i18n/hr.po
odoo/addons/l10n_it_pec/i18n/hr_HR.po
odoo/addons/l10n_it_pec/i18n/hu.po
odoo/addons/l10n_it_pec/i18n/it.po
odoo/addons/l10n_it_pec/i18n/ja.po
odoo/addons/l10n_it_pec/i18n/l10n_it_pec.pot
odoo/addons/l10n_it_pec/i18n/lt.po
odoo/addons/l10n_it_pec/i18n/lv.po
odoo/addons/l10n_it_pec/i18n/mk.po
odoo/addons/l10n_it_pec/i18n/mn.po
odoo/addons/l10n_it_pec/i18n/nb.po
odoo/addons/l10n_it_pec/i18n/nb_NO.po
odoo/addons/l10n_it_pec/i18n/nl.po
odoo/addons/l10n_it_pec/i18n/nl_BE.po
odoo/addons/l10n_it_pec/i18n/pl.po
odoo/addons/l10n_it_pec/i18n/pt.po
odoo/addons/l10n_it_pec/i18n/pt_BR.po
odoo/addons/l10n_it_pec/i18n/pt_PT.po
odoo/addons/l10n_it_pec/i18n/ro.po
odoo/addons/l10n_it_pec/i18n/ru.po
odoo/addons/l10n_it_pec/i18n/sl.po
odoo/addons/l10n_it_pec/i18n/sr@latin.po
odoo/addons/l10n_it_pec/i18n/sv.po
odoo/addons/l10n_it_pec/i18n/th.po
odoo/addons/l10n_it_pec/i18n/tr.po
odoo/addons/l10n_it_pec/i18n/vi.po
odoo/addons/l10n_it_pec/i18n/zh_CN.po
odoo/addons/l10n_it_pec/i18n/zh_TW.po
odoo/addons/l10n_it_pec/models/__init__.py
odoo_addon_l10n_it_pec-16.0.1.0.0.7.dist-info/METADATA
odoo_addon_l10n_it_pec-16.0.1.0.0.7.dist-info/WHEEL
odoo_addon_l10n_it_pec-16.0.1.0.0.7.dist-info/top_level.txt
odoo_addon_l10n_it_pec-16.0.1.0.0.7.dist-info/RECORD
